stringshift/__init__.py
stringshift/__main__.py
stringshift/cli.py
stringshift/core.py
stringshift/exceptions.py
stringshift-0.1.2.dist-info/METADATA
stringshift-0.1.2.dist-info/WHEEL
stringshift-0.1.2.dist-info/entry_points.txt
stringshift-0.1.2.dist-info/top_level.txt
stringshift-0.1.2.dist-info/RECORD
