Metadata-Version: 2.4
Name: stringshift
Version: 0.1.2
Summary: Advanced string encoding/decoding toolkit with parallel processing, auto-detection, and 12+ format support (URL, HTML, Base64, Morse, etc.)
Author-email: 0xdivin3 <chukwuebukawilliams6@gmail.com>
License: MIT
Project-URL: Homepage, https://github.com/0xdivin3/stringshift
Project-URL: Documentation, https://github.com/0xdivin3/stringshift/wiki
Project-URL: Repository, https://github.com/0xdivin3/stringshift
Project-URL: BugTracker, https://github.com/0xdivin3/stringshift/issues
Project-URL: Changelog, https://github.com/0xdivin3/stringshift/releases
Keywords: text-processing,encoding,decoding,url-decode,html-entities,unicode,text-conversion
Classifier: Development Status :: 4 - Beta
Classifier: Programming Language :: Python :: 3
Classifier: Programming Language :: Python :: 3.8
Classifier: Programming Language :: Python :: 3.9
Classifier: Programming Language :: Python :: 3.10
Classifier: Programming Language :: Python :: 3.11
Classifier: Intended Audience :: Developers
Classifier: License :: OSI Approved :: MIT License
Classifier: Operating System :: OS Independent
Classifier: Topic :: Software Development :: Libraries :: Python Modules
Classifier: Topic :: Text Processing :: Filters
Requires-Python: >=3.8
Requires-Dist: charset-normalizer>=2.0.0
Provides-Extra: full
Requires-Dist: chardet>=4.0.0; extra == "full"
Requires-Dist: python-dotenv>=0.19.0; extra == "full"
Requires-Dist: rich>=12.0.0; extra == "full"
Provides-Extra: test
Requires-Dist: pytest>=7.0.0; extra == "test"
Requires-Dist: pytest-cov>=3.0.0; extra == "test"
Requires-Dist: mypy>=0.950; extra == "test"
Provides-Extra: dev
Requires-Dist: black>=22.0.0; extra == "dev"
Requires-Dist: flake8>=4.0.0; extra == "dev"
Requires-Dist: isort>=5.0.0; extra == "dev"
